Metadata-Version: 2.1
Name: uploadsdemo
Version: 0.1
Summary: Gaussian distributions package for pypi upload
Home-page: UNKNOWN
License: UNKNOWN
Platform: UNKNOWN
